xspim_code/EX09/03/ALU.v
module  ALU(A,B,ALUoperation,ALUresult,Zero);   
     
input [31:0]     A;
input [31:0]     B;
input [3:0]      ALUoperation;
output [31:0]    ALUresult;
output           Zero;
     
reg    [31:0]    ALUresult;
wire   [32:0]    tmp;
     
      // Output Zero is defined by assign statement
     
      assign Zero = (ALUresult == 0)? 1'b1 : 1'b0;
     
      // tmp is the result of A - B, in 33bit
     
      assign tmp = {A[31], A} - {B[31], B};
     
      // Output ALUresult is defined by always statement
     
      always @(A or B or ALUoperation or tmp)
        begin case( ALUoperation )
          4'b0000 : ALUresult <= A & B;
          4'b0001 : ALUresult <= A | B;
          4'b0010 : ALUresult <= A + B;
          4'b0110 : ALUresult <= A - B;
          4'b0111 : ALUresult <= {31'b0, tmp[32]};
          4'b1100 : ALUresult <= (~A) & (~B);
          default : ALUresult <= 32'b0;
       endcase
      end
     
endmodule

xspim_code/HDL/ALUtestbench.v
`timescale 1ns/1ps     
     
`include "ALU.v"   // Include statement of ALU module  
     
module  ALUtestbench;   // testbench module ALUtestbench do not have inputs and output
     
reg [31:0]     inA;
reg [31:0]     inB;
reg [3:0]      inALUop;
wire [31:0]    outALUresult;
wire           outZero;
     
ALU     alu(inA,inB,inALUop,outALUresult,outZero); // Instance definition
     
initial     
 begin     
     
  $dumpfile("ALUtestbench.vcd"); //Function call for the save of execution results as VCD format to     
  $dumpvars(0, alu); //Function call to specify the top module     
     

  // AND op
  #0 inALUop = 4'b0000;

  inA= 32'h00000000; inB = 32'h00000000;      //Setting of inputs
  #100           
  $display( $time, " ALUoperation=%h, A=%h, B=%h, ALUresult=%h, Zero=%h",inALUop,inA,inB,outALUresult,outZero);         

  inA= 32'h0F0F0F0F; inB = 32'hF0F0F0F0;           
  #100           
  $display( $time, " ALUoperation=%h, A=%h, B=%h, ALUresult=%h, Zero=%h",inALUop,inA,inB,outALUresult,outZero);    
     
  inA= 32'hf0f0f0f0; inB = 32'h0f0f0f0f;           
  #100           
  $display( $time, " ALUoperation=%h, A=%h, B=%h, ALUresult=%h, Zero=%h",inALUop,inA,inB,outALUresult,outZero); 

  inA= 32'hFFFFFFFF; inB = 32'hFFFFFFFF;           
  #100           
  $display( $time, " ALUoperation=%h, A=%h, B=%h, ALUresult=%h, Zero=%h",inALUop,inA,inB,outALUresult,outZero); 

  inA= 32'hD8A3B8D4; inB = 32'h63B9D6F2;           
  #100           
  $display( $time, " ALUoperation=%h, A=%h, B=%h, ALUresult=%h, Zero=%h",inALUop,inA,inB,outALUresult,outZero); 
     
  
  // OR op
  #0 inALUop = 4'b0001;

  inA= 32'h00000000; inB = 32'h00000000;      //Setting of inputs
  #100           
  $display( $time, " ALUoperation=%h, A=%h, B=%h, ALUresult=%h, Zero=%h",inALUop,inA,inB,outALUresult,outZero);         

  inA= 32'h0F0F0F0F; inB = 32'hF0F0F0F0;           
  #100           
  $display( $time, " ALUoperation=%h, A=%h, B=%h, ALUresult=%h, Zero=%h",inALUop,inA,inB,outALUresult,outZero);    
     
  inA= 32'hf0f0f0f0; inB = 32'h0f0f0f0f;           
  #100           
  $display( $time, " ALUoperation=%h, A=%h, B=%h, ALUresult=%h, Zero=%h",inALUop,inA,inB,outALUresult,outZero); 

  inA= 32'hFFFFFFFF; inB = 32'hFFFFFFFF;           
  #100           
  $display( $time, " ALUoperation=%h, A=%h, B=%h, ALUresult=%h, Zero=%h",inALUop,inA,inB,outALUresult,outZero); 

  inA= 32'hD8A3B8D4; inB = 32'h63B9D6F2;           
  #100           
  $display( $time, " ALUoperation=%h, A=%h, B=%h, ALUresult=%h, Zero=%h",inALUop,inA,inB,outALUresult,outZero); 


  // ADD op
  #0 inALUop = 4'b0010;

  inA= 32'h00000000; inB = 32'h00000000;      //Setting of inputs
  #100           
  $display( $time, " ALUoperation=%h, A=%h, B=%h, ALUresult=%h, Zero=%h",inALUop,inA,inB,outALUresult,outZero);         

  inA= 32'h0F0F0F0F; inB = 32'hF0F0F0F0;           
  #100           
  $display( $time, " ALUoperation=%h, A=%h, B=%h, ALUresult=%h, Zero=%h",inALUop,inA,inB,outALUresult,outZero);    
     
  inA= 32'h7FFFFFFF; inB = 32'h00000001;           
  #100           
  $display( $time, " ALUoperation=%h, A=%h, B=%h, ALUresult=%h, Zero=%h",inALUop,inA,inB,outALUresult,outZero); 

  inA= 32'hFFFFFFFF; inB = 32'h00000001;           
  #100           
  $display( $time, " ALUoperation=%h, A=%h, B=%h, ALUresult=%h, Zero=%h",inALUop,inA,inB,outALUresult,outZero); 

  inA= 32'hD8A3B8D4; inB = 32'h63B9D6F2;           
  #100           
  $display( $time, " ALUoperation=%h, A=%h, B=%h, ALUresult=%h, Zero=%h",inALUop,inA,inB,outALUresult,outZero); 


  // SUB op
  #0 inALUop = 4'b0110;

  inA= 32'h00000000; inB = 32'h00000000;      //Setting of inputs
  #100           
  $display( $time, " ALUoperation=%h, A=%h, B=%h, ALUresult=%h, Zero=%h",inALUop,inA,inB,outALUresult,outZero);         

  inA= 32'h00000000; inB = 32'h00000001;           
  #100           
  $display( $time, " ALUoperation=%h, A=%h, B=%h, ALUresult=%h, Zero=%h",inALUop,inA,inB,outALUresult,outZero);    
     
  inA= 32'h00000001; inB = 32'h80000001;           
  #100           
  $display( $time, " ALUoperation=%h, A=%h, B=%h, ALUresult=%h, Zero=%h",inALUop,inA,inB,outALUresult,outZero); 

  inA= 32'h00000001; inB = 32'h00000001;           
  #100           
  $display( $time, " ALUoperation=%h, A=%h, B=%h, ALUresult=%h, Zero=%h",inALUop,inA,inB,outALUresult,outZero); 

  inA= 32'hD8A3B8D4; inB = 32'h63B9D6F2;           
  #100           
  $display( $time, " ALUoperation=%h, A=%h, B=%h, ALUresult=%h, Zero=%h",inALUop,inA,inB,outALUresult,outZero); 


  // SLT op
  #0 inALUop = 4'b0111;

  inA= 32'h00000000; inB = 32'h00000000;      //Setting of inputs
  #100           
  $display( $time, " ALUoperation=%h, A=%h, B=%h, ALUresult=%h, Zero=%h",inALUop,inA,inB,outALUresult,outZero);         

  inA= 32'h00000000; inB = 32'h00000001;           
  #100           
  $display( $time, " ALUoperation=%h, A=%h, B=%h, ALUresult=%h, Zero=%h",inALUop,inA,inB,outALUresult,outZero);    
     
  inA= 32'h00000001; inB = 32'h80000001;           
  #100           
  $display( $time, " ALUoperation=%h, A=%h, B=%h, ALUresult=%h, Zero=%h",inALUop,inA,inB,outALUresult,outZero); 

  inA= 32'h00000001; inB = 32'h00000001;           
  #100           
  $display( $time, " ALUoperation=%h, A=%h, B=%h, ALUresult=%h, Zero=%h",inALUop,inA,inB,outALUresult,outZero); 

  inA= 32'hD8A3B8D4; inB = 32'h63B9D6F2;           
  #100           
  $display( $time, " ALUoperation=%h, A=%h, B=%h, ALUresult=%h, Zero=%h",inALUop,inA,inB,outALUresult,outZero); 


  // NOR op
  #0 inALUop = 4'b1100;

  inA= 32'h00000000; inB = 32'h00000000;      //Setting of inputs
  #100           
  $display( $time, " ALUoperation=%h, A=%h, B=%h, ALUresult=%h, Zero=%h",inALUop,inA,inB,outALUresult,outZero);         

  inA= 32'h0F0F0F0F; inB = 32'hFFFFFFFF;           
  #100           
  $display( $time, " ALUoperation=%h, A=%h, B=%h, ALUresult=%h, Zero=%h",inALUop,inA,inB,outALUresult,outZero);    
     
  inA= 32'hf0f0f0f0; inB = 32'h0f0f0f0f;           
  #100           
  $display( $time, " ALUoperation=%h, A=%h, B=%h, ALUresult=%h, Zero=%h",inALUop,inA,inB,outALUresult,outZero); 

  inA= 32'hFFFFFFFF; inB = 32'hFFFFFFFF;           
  #100           
  $display( $time, " ALUoperation=%h, A=%h, B=%h, ALUresult=%h, Zero=%h",inALUop,inA,inB,outALUresult,outZero); 

  inA= 32'hD8A3B8D4; inB = 32'h63B9D6F2;           
  #100           
  $display( $time, " ALUoperation=%h, A=%h, B=%h, ALUresult=%h, Zero=%h",inALUop,inA,inB,outALUresult,outZero); 




  inALUop = 4'b0000; inA= 32'h00000000; inB = 32'h00000000; // dummy input
  $finish;      
 end     
endmodule

xspim_code/HDL/ALUtestbench.vcd
$date
    Apr 20, 2012  11:29:18
$end
$version
    Tool:	VERILOG-XL	05.83.003-p
$end
$timescale
     1ps
$end

$scope module ALUtestbench $end

$scope module alu $end
$var wire     32 !    A [31:0] $end
$var wire     32 "    B [31:0] $end
$var wire      4 #    ALUoperation [3:0] $end
$var wire      1 $    Zero  $end
$var reg      32 %    ALUresult [31:0] $end
$var wire     33 &    tmp [32:0] $end
$upscope $end

$upscope $end

$enddefinitions $end
$dumpvars
b00000000000000000000000000000000 !
b00000000000000000000000000000000 "
b0000 #
1$
b00000000000000000000000000000000 %
b000000000000000000000000000000000 &
$end
#100000
b00001111000011110000111100001111 !
b11110000111100001111000011110000 "
b000011110000111100001111000011111 &
#200000
b11110000111100001111000011110000 !
b00001111000011110000111100001111 "
b111100001111000011110000111100001 &
#300000
b11111111111111111111111111111111 !
b11111111111111111111111111111111 "
b000000000000000000000000000000000 &
b11111111111111111111111111111111 %
0$
#400000
b11011000101000111011100011010100 !
b01100011101110011101011011110010 "
b101110100111010011110000111100010 &
b01000000101000011001000011010000 %
#500000
b0001 #
b00000000000000000000000000000000 !
b00000000000000000000000000000000 "
b000000000000000000000000000000000 &
b00000000000000000000000000000000 %
1$
#600000
b00001111000011110000111100001111 !
b11110000111100001111000011110000 "
b000011110000111100001111000011111 &
b11111111111111111111111111111111 %
0$
#700000
b11110000111100001111000011110000 !
b00001111000011110000111100001111 "
b111100001111000011110000111100001 &
#800000
b11111111111111111111111111111111 !
b11111111111111111111111111111111 "
b000000000000000000000000000000000 &
#900000
b11011000101000111011100011010100 !
b01100011101110011101011011110010 "
b101110100111010011110000111100010 &
b11111011101110111111111011110110 %
#1000000
b0010 #
b00000000000000000000000000000000 !
b00000000000000000000000000000000 "
b000000000000000000000000000000000 &
b00000000000000000000000000000000 %
1$
#1100000
b00001111000011110000111100001111 !
b11110000111100001111000011110000 "
b000011110000111100001111000011111 &
b11111111111111111111111111111111 %
0$
#1200000
b01111111111111111111111111111111 !
b00000000000000000000000000000001 "
b001111111111111111111111111111110 &
b10000000000000000000000000000000 %
#1300000
b11111111111111111111111111111111 !
b111111111111111111111111111111110 &
b00000000000000000000000000000000 %
1$
#1400000
b11011000101000111011100011010100 !
b01100011101110011101011011110010 "
b101110100111010011110000111100010 &
b00111100010111011000111111000110 %
0$
#1500000
b0110 #
b00000000000000000000000000000000 !
b00000000000000000000000000000000 "
b000000000000000000000000000000000 &
b00000000000000000000000000000000 %
1$
#1600000
b00000000000000000000000000000001 "
b111111111111111111111111111111111 &
b11111111111111111111111111111111 %
0$
#1700000
b00000000000000000000000000000001 !
b10000000000000000000000000000001 "
b010000000000000000000000000000000 &
b10000000000000000000000000000000 %
#1800000
b00000000000000000000000000000001 "
b000000000000000000000000000000000 &
b00000000000000000000000000000000 %
1$
#1900000
b11011000101000111011100011010100 !
b01100011101110011101011011110010 "
b101110100111010011110000111100010 &
b01110100111010011110000111100010 %
0$
#2000000
b0111 #
b00000000000000000000000000000000 !
b00000000000000000000000000000000 "
b000000000000000000000000000000000 &
b00000000000000000000000000000000 %
1$
#2100000
b00000000000000000000000000000001 "
b111111111111111111111111111111111 &
b00000000000000000000000000000001 %
0$
#2200000
b00000000000000000000000000000001 !
b10000000000000000000000000000001 "
b010000000000000000000000000000000 &
b00000000000000000000000000000000 %
1$
#2300000
b00000000000000000000000000000001 "
b000000000000000000000000000000000 &
#2400000
b11011000101000111011100011010100 !
b01100011101110011101011011110010 "
b101110100111010011110000111100010 &
b00000000000000000000000000000001 %
0$
#2500000
b1100 #
b00000000000000000000000000000000 !
b00000000000000000000000000000000 "
b000000000000000000000000000000000 &
b11111111111111111111111111111111 %
#2600000
b00001111000011110000111100001111 !
b11111111111111111111111111111111 "
b000001111000011110000111100010000 &
b00000000000000000000000000000000 %
1$
#2700000
b11110000111100001111000011110000 !
b00001111000011110000111100001111 "
b111100001111000011110000111100001 &
#2800000
b11111111111111111111111111111111 !
b11111111111111111111111111111111 "
b000000000000000000000000000000000 &
#2900000
b11011000101000111011100011010100 !
b01100011101110011101011011110010 "
b101110100111010011110000111100010 &
b00000100010001000000000100001001 %
0$
