xspim_code/EX08/02/ALUcontrol.v
module ALUcontrol(ALUop, FA, FB, ALUoperation);

input [1:0] ALUop;
input [5:0] FA; // 5-0
input [5:0] FB; // 31-26
output [3:0] ALUoperation;
reg [3:0] ALUoperation;

always @(ALUop or FA or FB)
begin

 if(ALUop == 2'b00) ALUoperation <= 4'b0010;

 else if(ALUop == 2'b01) ALUoperation <= 4'b0110;

 else if(ALUop == 2'b10)
  begin
   if(FA == 6'b100000) ALUoperation <= 4'b0010;
   else if(FA == 6'b100010) ALUoperation <= 4'b0110;
   else if(FA == 6'b100100) ALUoperation <= 4'b0000;
   else if(FA == 6'b100101) ALUoperation <= 4'b0001;
   else if(FA == 6'b101010) ALUoperation <= 4'b0111;
  end

 else if(ALUop == 2'b11)
  begin
   if(FB == 6'b001000) ALUoperation <= 4'b0010;
   else if(FB == 6'b001100) ALUoperation <= 4'b0000;
   else if(FB == 6'b001101) ALUoperation <= 4'b0001;
   else if(FB == 6'b001010) ALUoperation <= 4'b0111;
  end 

end


/*
input [1:0]     ALUop;
input [5:0]     FA;// {F5,F4,F3,F2,F1,F0}
input [5:0]     FB;// {F31,F30,F29,F28,F27,F26}
output [3:0]    ALUoperation;
     
wire        ALUoperation0, ALUoperation1, ALUoperation2;
     
      assign ALUoperation0 = (ALUop[1] && ~ALUop[0] && FA[0]) || (ALUop[1] && ~ALUop[0] && FA[3]) || (ALUop[1] && ALUop[0] && FB[0]) || (ALUop[1] && ALUop[0] && FB[1]);
   
      assign ALUoperation1 = (~ALUop[1]) || (~ALUop[0] && ~FA[2]) || (ALUop[0] && ~FB[2]);
   
      assign ALUoperation2 = ( ~ALUop[1] && ALUop[0]) || (ALUop[1] && ~ALUop[0] && FA[1]) || (ALUop[1] && ALUop[0] && FB[1])  ;    
 
      assign ALUoperation = {1'b0, ALUoperation2, ALUoperation1, ALUoperation0};
*/

endmodule

xspim_code/EX09/03/ALU.v
module  ALU(A,B,ALUoperation,ALUresult,Zero);   
     
input [31:0]     A;
input [31:0]     B;
input [3:0]      ALUoperation;
output [31:0]    ALUresult;
output           Zero;
     
reg    [31:0]    ALUresult;
wire   [32:0]    tmp;
     
      // Output Zero is defined by assign statement
     
      assign Zero = (ALUresult == 0)? 1'b1 : 1'b0;
     
      // tmp is the result of A - B, in 33bit
     
      assign tmp = {A[31], A} - {B[31], B};
     
      // Output ALUresult is defined by always statement
     
      always @(A or B or ALUoperation or tmp)
        begin case( ALUoperation )
          4'b0000 : ALUresult <= A & B;
          4'b0001 : ALUresult <= A | B;
          4'b0010 : ALUresult <= A + B;
          4'b0110 : ALUresult <= A - B;
          4'b0111 : ALUresult <= {31'b0, tmp[32]};
          4'b1100 : ALUresult <= (~A) & (~B);
          default : ALUresult <= 32'b0;
       endcase
      end
     
endmodule

xspim_code/HDL/Registers.v
module Registers(ReadRegster1, ReadRegster2, WriteData, RegWrite, WriteRegster, CK, CLR, ReadData1, ReadData2);

input[4:0] 	ReadRegster1, ReadRegster2, WriteRegster;
input[31:0] 	WriteData;
input		RegWrite, CK, CLR;
output[31:0]	ReadData1, ReadData2;

reg[31:0]	regfile[1:31];
integer i;

always	@(posedge CK) begin
      if (CLR == 1'b1)
            for( i = 1; i < 31; i = i + 1)
                  regfile[i] <= 32'h00000000;
      else if ( RegWrite == 1'b1 && WriteRegster != 5'b00000)
                  regfile[WriteRegster] <= WriteData;
      end
 

assign #5 ReadData1 = (ReadRegster1 == 5'b00000) ? 32'h00000000 : regfile[ReadRegster1];
assign #5 ReadData2 = (ReadRegster2 == 5'b00000) ? 32'h00000000 : regfile[ReadRegster2];

endmodule

xspim_code/EX08/02/Memory.v
module Memory(Address, WriteData, ReadData, MemWrite, MemRead, CK);

input[31:0] 	Address, WriteData;
input           MemWrite, MemRead, CK;
output[31:0]	ReadData;

always @(posedge CK)
 begin 
   if (( MemWrite == 1'b1 ) && (32'h00000000 <= Address) && ( Address <= 32'h0000ffff) )
     begin
       Mem.cell[Address] = WriteData;
     end
 end

assign #5 ReadData = (MemRead == 1'b1) && (32'h00000000 <= Address) && ( Address <= 32'h0000ffff) ? Mem.cell[Address] : 32'bx;

endmodule


module Mem ();
  reg [31:0]  cell [0:65535];
endmodule

xspim_code/EX08/02/Datapath.v
`include "ALU.v"
`include "Memory.v"
`include "Registers.v" // Register File


module Datapath( CK, CLR, ALUOp, ALUSrcA, ALUSrcB, IRWrite, IorD, MemRead, MemWrite, MemtoReg, PCSource, PCWrite, PCWriteCond, RegDst, RegWrite, Op, Op2, ALUoperation);

input   CK;  
input   CLR;  
input [1:0]  ALUOp;  
input   ALUSrcA ;  
input [2:0]  ALUSrcB ;  
input   IRWrite ;  
input   IorD ;  
input   MemRead ;  
input   MemWrite ;  
input   MemtoReg ;  
input [1:0]  PCSource ;  
input   PCWrite ;  
input   PCWriteCond ;  
input   RegDst ;  
input   RegWrite ;
input [3:0] ALUoperation;
  
output [5:0]  Op ;
output [5:0] Op2;


reg [31:0] out_PC;
reg [31:0] out_mux3;
reg [31:0] ALUOut;
reg [31:0] out_mux2_1;
reg [4:0] out_mux2_2;
reg [31:0] out_mux2_3;
reg [31:0] out_mux2_4;
reg [31:0] out_mux5;
reg [31:0] A;
reg [31:0] B;
reg [31:0] MDR;
reg [31:0] InstReg;

wire PCload;
wire [31:0] from_ALU;
wire from_ALU_zero;
wire [31:0] from_RF1;
wire [31:0] from_RF2;
wire [31:0] from_memory;
wire [4:0] from_InstReg_25_21;
wire [4:0] from_InstReg_20_16;
wire [15:0] from_InstReg_15_0;


// PCload
assign PCload = (PCWrite | ( from_ALU_zero & PCWriteCond ));



// PC
always @(posedge CK)
begin
 if(CLR == 1'b1)
  out_PC <= 32'h00000000;
 else if(PCload == 1'b1)
  out_PC <= out_mux3;
end


// Multiplexor 2 to 1 (1)
always @(IorD or out_PC or ALUOut)
begin
 if(IorD == 1'b0) out_mux2_1 <= out_PC;
 else if(IorD == 1'b1) out_mux2_1 <= ALUOut;
 else out_mux2_1 <= 32'hxxxxxxxx; 
end


// Memory data
Memory _memory(out_mux2_1, B, from_memory, MemWrite, MemRead, CK);


// Instruction Register
always @(posedge CK or posedge CLR) 
begin
      if(CLR==1'b1) InstReg <= 32'h00000000;
     else if(IRWrite==1'b1) InstReg <= from_memory;
end

   assign Op = InstReg[31:26];
   assign Op2 = InstReg[5:0];
   assign from_InstReg_25_21 = InstReg[25:21];
   assign from_InstReg_20_16 = InstReg[20:16];
   assign from_InstReg_15_0 = InstReg[15:0];


// Multiplexor 2 to 1 (2)
always @(RegDst or from_InstReg_20_16 or from_InstReg_15_0)
begin
  if(RegDst == 1'b0) out_mux2_2 <= from_InstReg_20_16;
  else if(RegDst == 1'b1) out_mux2_2 <= from_InstReg_15_0[15:11];
end


// Multiplexor 2 to 1 (3)
always @(MemtoReg or ALUOut or MDR)
begin
  if(MemtoReg == 1'b0) out_mux2_3 <= ALUOut;
  else if(MemtoReg == 1'b1) out_mux2_3 <= MDR;
end


// Memory Data Register
always @(posedge CK or posedge CLR) 
begin
      MDR <= from_memory;
      if(CLR==1'b1) MDR <=32'h00000000;
end



// Register File
Registers RegFile(from_InstReg_25_21, from_InstReg_20_16, out_mux2_3, RegWrite, out_mux2_2, CK, CLR, from_RF1, from_RF2);


// A
/*
always @(posedge CK or posedge CLR) begin
      if(CLR == 1'b1)
        A <= 32'h00000000;
      else A <= from_RF1;
   end
*/
always @(from_RF1) begin
      A <= from_RF1;
   end



// B
always @(posedge CK or posedge CLR) begin
      if(CLR == 1'b1)
        B <= 32'h00000000;
      else B <= from_RF2;
   end

// Multiplexor 2 to 1 (4)
always @(ALUSrcA or out_PC or A)
begin
  if(ALUSrcA == 1'b0) out_mux2_4 <= out_PC;
  else if(ALUSrcA == 1'b1) out_mux2_4 <= A;
end


// Multiplexor 5 to 1
always @(ALUSrcB or B or from_InstReg_15_0)
begin
  if(ALUSrcB == 3'b000) out_mux5 <= B;
  else if(ALUSrcB == 3'b001) out_mux5 <= 32'd4;
  else if(ALUSrcB == 3'b010) out_mux5 <= {{16{from_InstReg_15_0[15]}}, from_InstReg_15_0};
  else if(ALUSrcB == 3'b011) out_mux5 <= {{14{from_InstReg_15_0[15]}}, from_InstReg_15_0, 2'b00};
  else if(ALUSrcB == 3'b100) out_mux5 <= {16'h0000, from_InstReg_15_0};
end


// ALU
ALU alu(out_mux2_4, out_mux5, ALUoperation, from_ALU, from_ALU_zero);


// ALUOut register
always @(posedge CK or posedge CLR)
begin
      if(CLR == 1'b1)
        ALUOut <= 32'h00000000;
      else ALUOut <= from_ALU;
end


// Multiplexor 3 to 1
always @(PCSource or from_ALU or ALUOut or out_PC or InstReg)
begin
  if(PCSource == 2'b00) out_mux3 <= from_ALU;
  else if(PCSource == 2'b01) out_mux3 <= ALUOut;
  else if(PCSource == 2'b10) out_mux3 <= {out_PC[31:28], InstReg[25:0], 2'b00};
end


endmodule

xspim_code/EX08/01/ControlUnit.v
`define LW 35
`define SW 43
`define RTYPE 0
`define BEQ 4
`define JMP 2
`define ADDI 8
`define SLTI 10
`define ANDI 12
`define ORI 13

// assign A = state == 0 || state == 1; これは if文で書く場合注意。ステート 0,1 以外の場合にも記述が必要。

module ControlUnit(PCWriteCond, PCWrite, IorD, MemRead, MemWrite, MemtoReg, IRWrite, PCSource, ALUOp, ALUSrcB, ALUSrcA, RegWrite, RegDST, Op, CK, CLR);

input CK;
input CLR;

output PCWriteCond;
output PCWrite;
output IorD;
output MemRead;
output MemWrite;
output MemtoReg;
output IRWrite;
output [1:0] PCSource;
output [1:0] ALUOp;
output [2:0] ALUSrcB;
output ALUSrcA;
output RegWrite;
output RegDST;


reg PCWriteCond;
reg PCWrite;
reg IorD;
reg MemRead;
reg MemWrite;
reg MemtoReg;
reg IRWrite;
reg [1:0] PCSource;
reg [1:0] ALUOp;
reg [2:0] ALUSrcB;
reg ALUSrcA;
reg RegWrite;
reg RegDST;


input [5:0] Op;

reg [3:0] state;


always @(posedge CK or posedge CLR)
begin
 if(CLR==1) state <= 0;
 else
  case(state)
   0: state <= 1;

   1:
    begin
     if(Op == `LW || Op == `SW)
      state <= 2;
     else if(Op == `RTYPE)
      state <= 6;
     else if(Op == `BEQ)
      state <= 8;
     else if(Op == `JMP)
      state <= 9;
     else if(Op == `ADDI || Op == `SLTI)
      state <= 10;
     else if(Op == `ANDI || Op == `ORI)
      state <= 12;
    end

   2:
    begin
     if(Op == `LW)
      state <= 3;
     else if(Op == `SW)
      state <= 5;
    end

   3: state <= 4;

   4: state <= 0;

   5: state <= 0;

   6: state <= 7;

   7: state <= 0;

   8: state <= 0;

   9: state <= 0;

   10: state <= 11;

   11: state <= 0;

   12: state <= 11;

   default: ;
  endcase
end


/*
assign MemRead = state == 0 || state == 3;

assign ALUSrcA = state == 0 ? 1'b0 : state == 1 ? 1'b0 : state == 2 ? 1'b1 : state == 6 ? 1'b1 : state == 8 ? 1'b1 : state == 10 ? 1'b1 : state == 12 ? 1'b1 : 1'bx;

assign IorD = state == 0 ? 1'b0 : state == 3 ? 1'b1 : state == 5 ? 1'b1 : 1'bx;

assign IRWrite = state == 0;

assign ALUSrcB = state == 0 ? 3'b001 : state == 1 ? 3'b011 : state == 2 ? 3'b010 : state == 6 ? 3'b000 : state == 8 ? 3'b000 : state == 10 ? 3'b010 : state == 12 ? 3'b100 : 3'bxxx;

assign ALUOp = state == 0 ? 2'b00 : state == 1 ? 2'b00 : state == 2 ? 2'b00 : state == 6 ? 2'b10 : state == 8 ? 2'b01 : state == 10 ? 2'b11 : state == 12 ? 2'b11 : 2'bxx;

assign PCWrite = state == 0 || state == 9;
assign PCSource = state == 0 ? 2'b00 : state == 8 ? 2'b01 : state == 9 ? 2'b10 : 2'bxx;
assign RegDST = state == 4 ? 1'b0 : state == 7 ? 1'b1 : state == 11 ? 1'b0 : 1'bx;
assign MemtoReg = state == 4 ? 1'b1 : state == 7 ? 1'b0 : state == 11 ? 1'b0 : 1'bx;
assign MemWrite = state == 5;
assign PCWriteCond = state == 8;
assign RegWrite = state == 4 || state == 7  || state == 11;
*/



always @(state)
begin
 case(state)
  0:
   begin
MemWrite <= 0;
PCWriteCond <= 0;
RegWrite <= 0;
    MemRead <= 1;
    ALUSrcA <= 1'b0;
    IorD <= 1'b0;
    IRWrite <= 1;
    ALUSrcB <= 3'b001;
    ALUOp <= 2'b00;
    PCWrite <= 1;
    PCSource <= 2'b00;
   end

  1:
   begin
    MemRead <= 0;
    IRWrite <= 0;
PCWrite <= 0;
MemWrite <= 0;
PCWriteCond <= 0;
RegWrite <= 0;
    ALUSrcA <= 1'b0;
    ALUSrcB <= 3'b011;
    ALUOp <= 2'b00;
   end

  2:
   begin
    MemRead <= 0;
IRWrite <= 0;
PCWrite <= 0;
MemWrite <= 0;
PCWriteCond <= 0;
RegWrite <= 0;
    ALUSrcA <= 1'b1;
    ALUSrcB <= 3'b010;
    ALUOp <= 2'b00;
   end

  3:
   begin
    MemRead <= 1;
IRWrite <= 0;
PCWrite <= 0;
MemWrite <= 0;
PCWriteCond <= 0;
RegWrite <= 0;
    IorD <= 1'b1;
   end

  4:
   begin
    MemRead <= 0;
IRWrite <= 0;
PCWrite <= 0;
MemWrite <= 0;
PCWriteCond <= 0;
    RegDST <= 1'b0;
    RegWrite <= 1;
    MemtoReg <= 1'b1;
   end

  5:
   begin
    MemRead <= 0;
IRWrite <= 0;
PCWrite <= 0;
PCWriteCond <= 0;
RegWrite <= 0;
    MemWrite <= 1;
    IorD <= 1'b1;
   end

  6:
   begin
    MemRead <= 0;
IRWrite <= 0;
PCWrite <= 0;
MemWrite <= 0;
PCWriteCond <= 0;
RegWrite <= 0;
    ALUSrcA <= 1'b1;
    ALUSrcB <= 3'b000;
    ALUOp <= 2'b10;
   end

  7:
   begin
    MemRead <= 0;
IRWrite <= 0;
PCWrite <= 0;
MemWrite <= 0;
PCWriteCond <= 0;
    RegDST <= 1'b1;
    RegWrite <= 1;
    MemtoReg <= 1'b0;
   end

  8:
   begin
    MemRead <= 0;
IRWrite <= 0;
PCWrite <= 0;
MemWrite <= 0;
RegWrite <= 0;
    ALUSrcA <= 1'b1;
    ALUSrcB <= 3'b000;
    ALUOp <= 2'b01;
    PCWriteCond <= 1;
    PCSource <= 2'b01;
   end

  9:
   begin
    MemRead <= 0;
IRWrite <= 0;
MemWrite <= 0;
PCWriteCond <= 0;
RegWrite <= 0;
    PCWrite <= 1;
    PCSource <= 2'b10;
   end

  10:
   begin
    MemRead <= 0;
IRWrite <= 0;
PCWrite <= 0;
MemWrite <= 0;
PCWriteCond <= 0;
RegWrite <= 0;
    ALUSrcA <= 1'b1;
    ALUSrcB <= 3'b010;
    ALUOp <= 2'b11;
   end

  11:
   begin
 MemRead <= 0;
IRWrite <= 0;
PCWrite <= 0;
MemWrite <= 0;
PCWriteCond <= 0;
    RegDST <= 1'b0;
    RegWrite <= 1;
    MemtoReg <= 1'b0;
   end

  12:
   begin
MemRead <= 0;
IRWrite <= 0;
PCWrite <= 0;
MemWrite <= 0;
PCWriteCond <= 0;
RegWrite <= 0;
    ALUSrcA <= 1'b1;
    ALUSrcB <= 3'b100;
    ALUOp <= 2'b11;
   end

  default: ;
 endcase
end


endmodule

xspim_code/EX08/01/MIPSmulticycle.v
`include "ControlUnit.v"
`include "ALUcontrol.v"
`include "Datapath.v"

module MIPSmulticycle(CK, CLR);

input CK;
input CLR;

wire [1:0] wALUOp;
wire wALUSrcA;
wire [2:0] wALUSrcB;
wire wIRWrite ;  
wire wIorD ;  
wire wMemRead ;  
wire wMemWrite ;  
wire wMemtoReg ;  
wire [1:0] wPCSource ;  
wire wPCWrite ;  
wire wPCWriteCond ;  
wire wRegDst ;  
wire wRegWrite ;  
wire [5:0] wOp ;
wire [5:0] wOp2;
wire [3:0] wALUoperation;
wire [31:0] wInstReg;


ControlUnit main_cont_unit(wPCWriteCond, wPCWrite, wIorD, wMemRead, wMemWrite, wMemtoReg, wIRWrite, wPCSource, wALUOp, wALUSrcB, wALUSrcA, wRegWrite, wRegDst, wOp, CK, CLR);

Datapath data_path(CK, CLR, wALUOp, wALUSrcA, wALUSrcB, wIRWrite, wIorD, wMemRead, wMemWrite, wMemtoReg, wPCSource, wPCWrite, wPCWriteCond, wRegDst, wRegWrite, wOp, wOp2, wALUoperation);

ALUcontrol alu_cont_unit(wALUOp, wOp2, wOp, wALUoperation);


endmodule

xspim_code/EX08/01/ex4bench.v
`timescale 1ns/1ps

`include "MIPSmulticycle.v"

module ex4bench;

reg CK;
reg CLR;

MIPSmulticycle mips_mul(CK,CLR);

initial
begin

$dumpfile("ex4bench.vcd"); //Function call for the save of execution results as VCD format to     
$dumpvars(0, mips_mul); //Function call to specify the top module

// text segment
Mem.cell['h00000000] = 32'h08000400;   // j 0x1000

Mem.cell['h00001000] = 32'h8c085000;   // lw $8, 20480($0) [A]            ; 8: lw $t0,A           # multiplier :A
Mem.cell['h00001004] = 32'h8c095004;   // lw $9, 20484($0) [B]            ; 9: lw $t1,B           # multiplicand :B
Mem.cell['h00001008] = 32'h00005025;   // or $10, $0, $0                  ; 10: or $t2,$zero,$zero # product :C
Mem.cell['h0000100c] = 32'h200c0001;   // addi $12, $0, 1                 ; 11: addi $t4,$zero,1   # tmp left shift 1,2,4,8....
Mem.cell['h00001010] = 32'h8c19500c;   // lw $25, 20492($0) [N]           ; 12: lw $t9,N           # max num for end loop
Mem.cell['h00001014] = 32'h31080001;   // andi $8, $8, 1                  ; 14: andi $t0,$t0,1       # get multiplier.0
Mem.cell['h00001018] = 32'h11000001;   // beq $8, $0, 4 [step2-0x00001018]; 15: beq $t0,$zero,step2  # multiplier.0 == 0, goto step2
Mem.cell['h0000101c] = 32'h01495020;   // add $10, $10, $9                ; 16: add $t2,$t2,$t1      # add product :C
Mem.cell['h00001020] = 32'h01294820;   // add $9, $9, $9                  ; 18: add $t1,$t1,$t1 # shift left
Mem.cell['h00001024] = 32'h018c6020;   // add $12, $12, $12               ; 21: add $t4,$t4,$t4 # shift right 1 (shift left)
Mem.cell['h00001028] = 32'h8c085000;   // lw $8, 20480($0) [A]            ; 22: lw $t0,A         # shift right 2 (reload A)
Mem.cell['h0000102c] = 32'h010c4024;   // and $8, $8, $12                 ; 23: and $t0,$t0,$t4  # shift right 3 (get next multiplier)
Mem.cell['h00001030] = 32'h0199682a;   // slt $13, $12, $25               ; 25: slt $t5,$t4,$t9        # counter check if [ $t4 < multiplier(A) ]
Mem.cell['h00001034] = 32'h11a00001;   // beq $13, $0, 4 [loopend-0x00001034]; 26: beq $t5,$zero,loopend  # if $t4 > A, loopend
Mem.cell['h00001038] = 32'h08000406;   // j 0x00001018 [step1]            ; 27: j step1                # otherwise, goto step1
Mem.cell['h0000103c] = 32'hac0a5008;   // sw $10, 20488($0) [C]           ; 29: sw $t2,C        # store product in C
Mem.cell['h00001040] = 32'h08000410;   // j 0x00001040 [exit]             ; 31: j exit

// data segment
Mem.cell['h00005000] = 32'h0000000d;
Mem.cell['h00005004] = 32'h00000025;
Mem.cell['h00005008] = 32'h00000000;
Mem.cell['h0000500c] = 32'h00000020;

CK = 1'b1;
CLR = 1'b1;

#110

CLR = 1'b0;

#20000
   $display("RESULT:");
   $display("mul:  %x",Mem.cell['h00005008]);
$finish;
end

always #50 CK <= ~CK;

endmodule

xspim_code/EX08/01/ex4bench.vcd
$date
    Jun  6, 2012  12:57:58
$end
$version
    TOOL:	ncsim	10.20-s073
$end
$timescale
    1 ps
$end

$scope module ex4bench $end

$scope module mips_mul $end
$var wire      1 !    CK  $end
$var wire      1 "    CLR  $end
$var wire      2 #    wALUOp [1:0] $end
$var wire      1 $    wALUSrcA  $end
$var wire      3 %    wALUSrcB [2:0] $end
$var wire      1 &    wIRWrite  $end
$var wire      1 '    wIorD  $end
$var wire      1 (    wMemRead  $end
$var wire      1 )    wMemWrite  $end
$var wire      1 *    wMemtoReg  $end
$var wire      2 +    wPCSource [1:0] $end
$var wire      1 ,    wPCWrite  $end
$var wire      1 -    wPCWriteCond  $end
$var wire      1 .    wRegDst  $end
$var wire      1 /    wRegWrite  $end
$var wire      6 0    wOp [5:0] $end
$var wire      6 1    wOp2 [5:0] $end
$var wire      4 2    wALUoperation [3:0] $end
$var wire     32 3    wInstReg [31:0] $end

$scope module main_cont_unit $end
$var wire      1 !    CK  $end
$var wire      1 "    CLR  $end
$var reg       1 4    PCWriteCond  $end
$var reg       1 5    PCWrite  $end
$var reg       1 6    IorD  $end
$var reg       1 7    MemRead  $end
$var reg       1 8    MemWrite  $end
$var reg       1 9    MemtoReg  $end
$var reg       1 :    IRWrite  $end
$var reg       2 ;    PCSource [1:0] $end
$var reg       2 <    ALUOp [1:0] $end
$var reg       3 =    ALUSrcB [2:0] $end
$var reg       1 >    ALUSrcA  $end
$var reg       1 ?    RegWrite  $end
$var reg       1 @    RegDST  $end
$var wire      6 0    Op [5:0] $end
$var reg       4 A    state [3:0] $end
$upscope $end


$scope module data_path $end
$var wire      1 !    CK  $end
$var wire      1 "    CLR  $end
$var wire      2 #    ALUOp [1:0] $end
$var wire      1 $    ALUSrcA  $end
$var wire      3 %    ALUSrcB [2:0] $end
$var wire      1 &    IRWrite  $end
$var wire      1 '    IorD  $end
$var wire      1 (    MemRead  $end
$var wire      1 )    MemWrite  $end
$var wire      1 *    MemtoReg  $end
$var wire      2 +    PCSource [1:0] $end
$var wire      1 ,    PCWrite  $end
$var wire      1 -    PCWriteCond  $end
$var wire      1 .    RegDst  $end
$var wire      1 /    RegWrite  $end
$var wire      4 2    ALUoperation [3:0] $end
$var wire      6 0    Op [5:0] $end
$var wire      6 1    Op2 [5:0] $end
$var reg      32 B    out_PC [31:0] $end
$var reg      32 C    out_mux3 [31:0] $end
$var reg      32 D    ALUOut [31:0] $end
$var reg      32 E    out_mux2_1 [31:0] $end
$var reg       5 F    out_mux2_2 [4:0] $end
$var reg      32 G    out_mux2_3 [31:0] $end
$var reg      32 H    out_mux2_4 [31:0] $end
$var reg      32 I    out_mux5 [31:0] $end
$var reg      32 J    A [31:0] $end
$var reg      32 K    B [31:0] $end
$var reg      32 L    MDR [31:0] $end
$var reg      32 M    InstReg [31:0] $end
$var wire      1 N    PCload  $end
$var wire     32 O    from_ALU [31:0] $end
$var wire      1 P    from_ALU_zero  $end
$var wire     32 Q    from_RF1 [31:0] $end
$var wire     32 R    from_RF2 [31:0] $end
$var wire     32 S    from_memory [31:0] $end
$var wire      5 T    from_InstReg_25_21 [4:0] $end
$var wire      5 U    from_InstReg_20_16 [4:0] $end
$var wire     16 V    from_InstReg_15_0 [15:0] $end

$scope module _memory $end
$var wire     32 W    Address [31:0] $end
$var wire     32 X    WriteData [31:0] $end
$var wire      1 )    MemWrite  $end
$var wire      1 (    MemRead  $end
$var wire      1 !    CK  $end
$var wire     32 S    ReadData [31:0] $end
$upscope $end


$scope module RegFile $end
$var wire      5 T    ReadRegster1 [4:0] $end
$var wire      5 U    ReadRegster2 [4:0] $end
$var wire      5 Y    WriteRegster [4:0] $end
$var wire     32 Z    WriteData [31:0] $end
$var wire      1 /    RegWrite  $end
$var wire      1 !    CK  $end
$var wire      1 "    CLR  $end
$var wire     32 Q    ReadData1 [31:0] $end
$var wire     32 R    ReadData2 [31:0] $end
$var integer  32 [    i  $end
$upscope $end


$scope module alu $end
$var wire     32 \    A [31:0] $end
$var wire     32 ]    B [31:0] $end
$var wire      4 2    ALUoperation [3:0] $end
$var reg      32 ^    ALUresult [31:0] $end
$var wire      1 P    Zero  $end
$var wire     33 _    tmp [32:0] $end
$upscope $end

$upscope $end


$scope module alu_cont_unit $end
$var wire      2 #    ALUop [1:0] $end
$var wire      6 1    FA [5:0] $end
$var wire      6 0    FB [5:0] $end
$var reg       4 `    ALUoperation [3:0] $end
$upscope $end

$upscope $end

$upscope $end

$enddefinitions $end
$dumpvars
1!
1"
b0 #
0$
b1 %
1&
0'
1(
0)
x*
b0 +
1,
0-
x.
0/
b0 0
b0 1
b10 2
bz 3
04
15
06
17
08
x9
1:
b0 ;
b0 <
b1 =
0>
0?
x@
b0 A
b0 B
b100 C
b0 D
b0 E
bx F
bx G
b0 H
b100 I
bx J
b0 K
b0 L
b0 M
1N
b100 O
0P
bx Q
bx R
bx S
b0 T
b0 U
b0 V
b0 W
b0 X
bx Y
bx Z
b11111 [
b0 \
b100 ]
b100 ^
b111111111111111111111111111111100 _
b10 `
$end
#5000
b1000000000000000010000000000 S
b0 Q
b0 R
b0 J
#50000
0!
#100000
1!
b1 [
b10 [
b11 [
b100 [
b101 [
b110 [
b111 [
b1000 [
b1001 [
b1010 [
b1011 [
b1100 [
b1101 [
b1110 [
b1111 [
b10000 [
b10001 [
b10010 [
b10011 [
b10100 [
b10101 [
b10110 [
b10111 [
b11000 [
b11001 [
b11010 [
b11011 [
b11100 [
b11101 [
b11110 [
b11111 [
#110000
0"
#150000
0!
#200000
1!
b100 D
b1000000000000000010000000000 L
b1000000000000000010000000000 M
b1 A
b100 B
b10000000000 V
b10 0
b100 E
07
0:
05
b11 =
b100 H
b100 \
b100 W
b11 %
0,
0&
0(
0N
b0 _
b1000 ^
b1000000000000 I
b1000000000000 ]
b1000 O
b111111111111111111111000000000100 _
b1000000000100 ^
b1000 C
b1000000000100 O
b1000000000100 C
#205000
bx S
#250000
0!
#300000
1!
b1000000000100 D
bx L
b1001 A
15
b10 ;
b10 +
1,
1N
b1000000000000 C
#350000
0!
#400000
1!
b0 A
b1000000000000 B
17
1:
b1 =
b0 ;
b1000000000000 E
b1000000000000 H
b1000000000000 \
b1000000000000 W
b0 +
b1 %
1&
1(
b0 _
b10000000000000 ^
b1000000000100 C
b100 I
b100 ]
b10000000000000 O
b111111111100 _
b1000000000100 ^
b10000000000000 C
b1000000000100 O
b1000000000100 C
#405000
b10001100000010000101000000000000 S
#450000
0!
#500000
1!
b10001100000010000101000000000000 L
b10001100000010000101000000000000 M
b1 A
b1000000000100 B
b101000000000000 V
b1000 U
b100011 0
07
0:
05
b11 =
b1000000000100 E
b1000000000100 H
b1000000000100 \
b1000000000100 W
b11 %
0,
0&
0(
0N
b1000000000000 _
b1000000001000 ^
b10100000000000000 I
b10100000000000000 ]
b1000000001000 O
b111111111111111101101000000000100 _
b10101000000000100 ^
b1000000001000 C
b10101000000000100 O
b10101000000000100 C
#505000
bx S
#550000
0!
#600000
1!
b10101000000000100 D
bx L
b10 A
1>
b10 =
b10 %
1$
b101000000000000 I
b0 H
b0 \
b101000000000000 ]
b111111111111111111011000000000000 _
b101000000000000 ^
b101000000000000 O
b101000000000000 C
#650000
0!
#700000
1!
b101000000000000 D
b11 A
17
16
1'
1(
b101000000000000 E
b101000000000000 W
#705000
b1101 S
#750000
0!
#800000
1!
b1101 L
b100 A
07
0@
1?
19
1*
1/
0.
0(
b1101 G
b1000 F
b1000 Y
b1101 Z
#805000
bx S
#850000
0!
#900000
1!
bx L
b0 A
bx G
0?
17
0>
06
1:
b1 =
15
bx Z
1,
b1 %
1&
0'
0$
1(
0/
1N
b100 I
b1000000000100 E
b1000000000100 H
b1000000000100 \
b1000000000100 W
b100 ]
b1000000000000 _
b1000000001000 ^
b1000000001000 O
b1000000001000 C
#905000
b10001100000010010101000000000100 S
b1101 R
#950000
0!
#1000000
1!
b1000000001000 D
b10001100000010010101000000000100 L
b1101 K
b10001100000010010101000000000100 M
b1 A
b1000000001000 B
b101000000000100 V
b1001 U
b100 1
b1101 X
b1000000001000 E
b10001100000010010101000000000100 G
07
0:
05
b11 =
b1000000001000 H
b1001 F
b1001 Y
b1000000001000 \
b10001100000010010101000000000100 Z
b1000000001000 W
b11 %
0,
0&
0(
0N
b1000000000100 _
b1000000001100 ^
b10100000000010000 I
b10100000000010000 ]
b1000000001100 O
b111111111111111101100111111111000 _
b10101000000011000 ^
b1000000001100 C
b10101000000011000 O
b10101000000011000 C
#1005000
bx S
b0 R
#1050000
0!
#1100000
1!
b10101000000011000 D
bx L
b0 K
b10 A
b0 X
bx G
1>
b10 =
bx Z
b10 %
1$
b101000000000100 I
b0 H
b0 \
b101000000000100 ]
b111111111111111111010111111111100 _
b101000000000100 ^
b101000000000100 O
b101000000000100 C
#1150000
0!
#1200000
1!
b101000000000100 D
b11 A
17
16
1'
1(
b101000000000100 E
b101000000000100 W
#1205000
b100101 S
#1250000
0!
#1300000
1!
b100101 L
b100 A
b100101 G
07
1?
b100101 Z
1/
0(
#1305000
bx S
#1350000
0!
#1400000
1!
bx L
b0 A
bx G
0?
17
0>
06
1:
b1 =
15
bx Z
1,
b1 %
1&
0'
0$
1(
0/
1N
b100 I
b1000000001000 E
b1000000001000 H
b1000000001000 \
b1000000001000 W
b100 ]
b1000000000100 _
b1000000001100 ^
b1000000001100 O
b1000000001100 C
#1405000
b101000000100101 S
b100101 R
#1450000
0!
#1500000
1!
b1000000001100 D
b101000000100101 L
b100101 K
b101000000100101 M
b1 A
b1000000001100 B
b101000000100101 V
b0 U
b100101 1
b0 0
b100101 X
b1000000001100 E
b101000000100101 G
07
0:
05
b11 =
b1000000001100 H
b0 F
b0 Y
b1000000001100 \
b101000000100101 Z
b1000000001100 W
b11 %
0,
0&
0(
0N
b1000000001000 _
b1000000010000 ^
b10100000010010100 I
b10100000010010100 ]
b1000000010000 O
b111111111111111101100111101111000 _
b10101000010100000 ^
b1000000010000 C
b10101000010100000 O
b10101000010100000 C
#1505000
bx S
b0 R
#1550000
0!
#1600000
1!
b10101000010100000 D
bx L
b0 K
b110 A
b0 X
bx G
1>
b0 =
b10 <
bx Z
b10 #
b0 %
1$
b1 `
b0 I
b0 H
b0 \
b0 ]
b1 2
b0 _
b0 ^
1P
b0 O
b0 C
#1650000
0!
